Qmlview/__init__.py
Qmlview/_qmlview_resource_.py
Qmlview/frame.py
Qmlview/func.py
Qmlview/misc.py
Qmlview/qmlview.py
Qmlview-3.2.1.dist-info/LICENSE
Qmlview-3.2.1.dist-info/METADATA
Qmlview-3.2.1.dist-info/WHEEL
Qmlview-3.2.1.dist-info/entry_points.txt
Qmlview-3.2.1.dist-info/top_level.txt
Qmlview-3.2.1.dist-info/RECORD
