Metadata-Version: 2.1
Name: Qmlview
Version: 3.2.1
Summary: An alternative to qmlscene
Home-page: https://github.com/amoh-godwin/Qmlview-wheel
Author: Amoh - Gyebi Godwin Ampofo Michael
Author-email: amohgyebigodwin@gmail.com
Project-URL: Bug Tracker, https://github.com/amoh-godwin/Qmlview-wheel/issues
Project-URL: Documentation, https://github.com/amoh-godwin/Qmlview-wheel/wiki
Project-URL: Source Code, https://github.com/amoh-godwin/Qmlview-wheel
Keywords: qmlview,qmlscene,ninja-preview,qml,pyqt,pyqt6,pyside,pyside6
Classifier: Programming Language :: Python
Classifier: Programming Language :: Python :: 3
Classifier: Development Status :: 5 - Production/Stable
Classifier: Environment :: Other Environment
Classifier: Intended Audience :: Developers
Classifier: License :: OSI Approved :: GNU Library or Lesser General Public License (LGPL)
Classifier: Operating System :: OS Independent
Classifier: Topic :: Software Development :: Libraries :: Python Modules
License-File: LICENSE
Requires-Dist: PyQt6-Qt6
Requires-Dist: PyQt6 (>=6.5.1)
